fastduck/__init__.py
fastduck/_modidx.py
fastduck/core.py
fastduck-0.0.14.dist-info/LICENSE
fastduck-0.0.14.dist-info/METADATA
fastduck-0.0.14.dist-info/WHEEL
fastduck-0.0.14.dist-info/entry_points.txt
fastduck-0.0.14.dist-info/top_level.txt
fastduck-0.0.14.dist-info/RECORD
