Metadata-Version: 2.1
Name: fastduck
Version: 0.0.14
Summary: A bit of extra usability for duckdb... inspired by fastlite and sqlite_utils
Home-page: https://github.com/fredguth/fastduck
Author: Fred Guth
Author-email: fredguth@fredguth.com
License: Apache Software License 2.0
Keywords: nbdev jupyter notebook python sql duckdb
Classifier: Development Status :: 4 - Beta
Classifier: Intended Audience :: Developers
Classifier: Natural Language :: English
Classifier: Programming Language :: Python :: 3.7
Classifier: Programming Language :: Python :: 3.8
Classifier: Programming Language :: Python :: 3.9
Classifier: Programming Language :: Python :: 3.10
Classifier: License :: OSI Approved :: Apache Software License
Requires-Python: >=3.7
License-File: LICENSE
Requires-Dist: fastcore
Requires-Dist: pandas
Requires-Dist: numpy
Requires-Dist: graphviz
Requires-Dist: pathlib
Requires-Dist: tabulate
Provides-Extra: dev
Requires-Dist: nbdev ; extra == 'dev'
Requires-Dist: setuptools ; extra == 'dev'
Requires-Dist: jedi ; extra == 'dev'
Requires-Dist: sql ; extra == 'dev'
Requires-Dist: ipykernel ; extra == 'dev'
Requires-Dist: ipython ; extra == 'dev'
Requires-Dist: jupyter ; extra == 'dev'
